text_clf/__init__.py
text_clf/__main__.py
text_clf/config.py
text_clf/data.py
text_clf/lemmatizer.py
text_clf/logger.py
text_clf/pr_roc_curve.py
text_clf/save.py
text_clf/token_frequency.py
text_clf/train.py
text_clf/utils.py
text_classification_baseline-0.1.6.dist-info/LICENSE
text_classification_baseline-0.1.6.dist-info/METADATA
text_classification_baseline-0.1.6.dist-info/WHEEL
text_classification_baseline-0.1.6.dist-info/entry_points.txt
text_classification_baseline-0.1.6.dist-info/top_level.txt
text_classification_baseline-0.1.6.dist-info/RECORD
