Metadata-Version: 2.1
Name: text-classification-baseline
Version: 0.1.6
Summary: TF-IDF + LogReg baseline for text classification
Home-page: https://github.com/dayyass/text-classification-baseline
Author: Dani El-Ayyass
Author-email: dayyass@yandex.ru
License: UNKNOWN
Project-URL: Bug Tracker, https://github.com/dayyass/text-classification-baseline/issues
Platform: UNKNOWN
Classifier: Programming Language :: Python :: 3
Classifier: License :: OSI Approved :: MIT License
Classifier: Operating System :: OS Independent
Requires-Python: >=3.6
License-File: LICENSE
Requires-Dist: numpy (>=1.19.5)
Requires-Dist: scipy (>=1.5.4)
Requires-Dist: pandas (>=1.1.5)
Requires-Dist: scikit-learn (>=0.24.2)
Requires-Dist: matplotlib (>=3.3.4)
Requires-Dist: pymorphy2 (>=0.9.1)
Requires-Dist: PyYAML (>=5.4.1)
